vidu_mcp/__init__.py
vidu_mcp/client.py
vidu_mcp/const.py
vidu_mcp/exceptions.py
vidu_mcp/server.py
vidu_mcp/util.py
vidu_mcp-0.1.2.dist-info/METADATA
vidu_mcp-0.1.2.dist-info/WHEEL
vidu_mcp-0.1.2.dist-info/entry_points.txt
vidu_mcp-0.1.2.dist-info/licenses/LICENSE
vidu_mcp-0.1.2.dist-info/RECORD
