Metadata-Version: 2.4
Name: vidu-mcp
Version: 0.1.2
Summary: Add your description here
Author-email: yuchen.zhao@shengshu.ai
License-File: LICENSE
Requires-Python: >=3.12
Requires-Dist: dotenv>=0.9.9
Requires-Dist: mcp>=1.9.4
Requires-Dist: requests>=2.32.4
